bruker_reader/__init__.py
bruker_reader/reader/reader.py
bruker_reader-0.1.3.dist-info/METADATA
bruker_reader-0.1.3.dist-info/WHEEL
bruker_reader-0.1.3.dist-info/licenses/LICENSE
bruker_reader-0.1.3.dist-info/licenses/LICENSE.txt
bruker_reader-0.1.3.dist-info/RECORD
