Metadata-Version: 2.3
Name: bruker-reader
Version: 0.1.3
Summary: Reader for Bruker FTICR BAF files
Author-email: theinfinitegirl <gretchenlynhall@gmail.com>
Requires-Python: >=3.8
Requires-Dist: numpy>=1.26.0
Requires-Dist: pandas>=2.1.1
